git_text_tree.py
git-text-tree/__init__.py
git-text-tree/cli.py
git-text-tree/hooks.py
git-text-tree/logger.py
git-text-tree/printer.py
git-text-tree/scanner.py
git-text-tree/utils.py
git_text_tree/__init__.py
git_text_tree/cli.py
git_text_tree/hooks.py
git_text_tree/logger.py
git_text_tree/printer.py
git_text_tree/scanner.py
git_text_tree/utils.py
git_text_tree-0.1.1.dist-info/LICENSE
git_text_tree-0.1.1.dist-info/METADATA
git_text_tree-0.1.1.dist-info/WHEEL
git_text_tree-0.1.1.dist-info/entry_points.txt
git_text_tree-0.1.1.dist-info/top_level.txt
git_text_tree-0.1.1.dist-info/RECORD
