Metadata-Version: 2.2
Name: git-text-tree
Version: 0.1.1
Summary: A tool to generate text-based representations of git repositories.
Home-page: https://github.com/Last-emo-boy/git-text-tree
Author: Chen Yuqian
Author-email: momoxiaomaster@gmail.com
License: MIT
Classifier: Programming Language :: Python :: 3
Classifier: License :: OSI Approved :: MIT License
Classifier: Operating System :: OS Independent
Requires-Python: >=3.6
License-File: LICENSE
Requires-Dist: pathspec
Dynamic: author
Dynamic: author-email
Dynamic: classifier
Dynamic: description
Dynamic: description-content-type
Dynamic: home-page
Dynamic: license
Dynamic: requires-dist
Dynamic: requires-python
Dynamic: summary
